<AML>
 <Item type="CAD_Mapping_Properties" id="D0D4B478D4514BE7AEEE1B69923EC0B4" action="add">
  <is_checkout>0</is_checkout>
  <is_model_config>0</is_model_config>
  <is_readonly>0</is_readonly>
  <is_required>1</is_required>
  <is_system>0</is_system>
  <mapping_field>documentnumber</mapping_field>
  <mapping_label>圖檔編號</mapping_label>
  <plm_field>item_number</plm_field>
  <sort_order>256</sort_order>
  <source_id keyed_name="SolidWorks Mechanical/Assembly" type="CADIntegration_Setting">7016C5BA7EAF443582AC57FFB655D987</source_id>
 </Item>
</AML>